genish.py
ccloud/__init__.py
ccloud/endpoints.py
ccloud/api/__init__.py
ccloud/api/g5k.py
geni/__init__.py
geni/_coreutil.py
geni/constants.py
geni/exceptions.py
geni/namespaces.py
geni/portal.py
geni/tempfile.py
geni/types.py
geni/urn.py
geni/util.py
geni/warnings.py
geni/admin/__init__.py
geni/admin/flowvisor.py
geni/admin/foam.py
geni/admin/germ.py
geni/admin/oess.py
geni/admin/vts.py
geni/aggregate/__init__.py
geni/aggregate/amtypes.py
geni/aggregate/apis.py
geni/aggregate/apt.py
geni/aggregate/cloudlab.py
geni/aggregate/context.py
geni/aggregate/core.py
geni/aggregate/core_openflow.py
geni/aggregate/exceptions.py
geni/aggregate/exogeni.py
geni/aggregate/frameworks.py
geni/aggregate/instageni.py
geni/aggregate/instageni_openflow.py
geni/aggregate/opengeni.py
geni/aggregate/pgutil.py
geni/aggregate/protogeni.py
geni/aggregate/spec.py
geni/aggregate/transit.py
geni/aggregate/user.py
geni/aggregate/vts.py
geni/minigcf/__init__.py
geni/minigcf/amapi2.py
geni/minigcf/amapi3.py
geni/minigcf/chapi2.py
geni/minigcf/config.py
geni/minigcf/pgch1.py
geni/minigcf/util.py
geni/model/__init__.py
geni/model/base.py
geni/model/compute.py
geni/model/util.py
geni/rspec/__init__.py
geni/rspec/base.py
geni/rspec/egext.py
geni/rspec/igext.py
geni/rspec/igutil.py
geni/rspec/oessad.py
geni/rspec/ofad.py
geni/rspec/ofrequest.py
geni/rspec/pg.py
geni/rspec/pgad.py
geni/rspec/pgmanifest.py
geni/rspec/stitching.py
geni/rspec/vts.py
geni/rspec/vtsad.py
geni/rspec/vtsmanifest.py
geni/rspec/emulab/__init__.py
geni/rspec/emulab/emuext.py
geni/rspec/emulab/enodeb.py
geni/rspec/emulab/epcexc.py
geni/rspec/emulab/epclan.py
geni/rspec/emulab/epcnode.py
geni/rspec/emulab/pndefs.py
geni/rspec/emulab/pnext.py
geni/rspec/emulab/rflink.py
geni/rspec/emulab/ue.py
geni/rspec/emulab/userdata.py
geni/support/__init__.py
geni/support/ipython.py
geni_lib-0.9.9.4.data/scripts/build-context
geni_lib-0.9.9.4.data/scripts/context-from-bundle
geni_lib-0.9.9.4.data/scripts/genish
geni_lib-0.9.9.4.dist-info/LICENSE
geni_lib-0.9.9.4.dist-info/METADATA
geni_lib-0.9.9.4.dist-info/WHEEL
geni_lib-0.9.9.4.dist-info/top_level.txt
geni_lib-0.9.9.4.dist-info/RECORD
