Metadata-Version: 2.1
Name: geni-lib
Version: 0.9.9.4
Summary: Library and tools for working with research testbed resources that support the GENI AM API, including the NSF GENI Testbed (www.geni.net) and Cloudlab (cloudlab.us).
Home-page: http://docs.uh-netlab.org/projects/geni-lib
Author: Nick Bastin
Author-email: nick@bssoftworks.com
License: UNKNOWN
Platform: UNKNOWN
Classifier: Development Status :: 5 - Production/Stable
Classifier: Environment :: Console
Classifier: Programming Language :: Python :: 2.7
Classifier: Programming Language :: Python :: 3.6
Classifier: License :: OSI Approved :: Mozilla Public License 2.0 (MPL 2.0)
Requires-Dist: cryptography
Requires-Dist: ipaddress
Requires-Dist: lxml
Requires-Dist: requests
Requires-Dist: wrapt
